causara/__init__.py
causara_ai_toolkit_for_gurobi-1.0.3.dist-info/LICENSE.txt
causara_ai_toolkit_for_gurobi-1.0.3.dist-info/METADATA
causara_ai_toolkit_for_gurobi-1.0.3.dist-info/WHEEL
causara_ai_toolkit_for_gurobi-1.0.3.dist-info/top_level.txt
causara_ai_toolkit_for_gurobi-1.0.3.dist-info/RECORD
