Metadata-Version: 2.1
Name: causara-ai-toolkit-for-gurobi
Version: 1.0.3
Summary: This package provides several AI-features for building and working with Gurobi optimization models.
Home-page: https://www.causara.com
Author: causara UG
Author-email: support@causara.com
License: Proprietary
Classifier: Programming Language :: Python :: 3
Classifier: License :: Other/Proprietary License
Classifier: Operating System :: OS Independent
Requires-Python: >=3.9, <3.13
License-File: LICENSE.txt
Requires-Dist: torch
Requires-Dist: bcrypt
Requires-Dist: numpy <2
Requires-Dist: scipy
Requires-Dist: gurobipy
Requires-Dist: pandas
Requires-Dist: openpyxl
Requires-Dist: reportlab
Requires-Dist: psutil
Requires-Dist: sympy
Requires-Dist: tqdm
Requires-Dist: pywebview
Requires-Dist: cefpython3
Requires-Dist: rdkit
Requires-Dist: matplotlib
Requires-Dist: folium
Requires-Dist: pyshortcuts
Requires-Dist: orjson
Requires-Dist: pyyaml
